insert_license_header/__init__.py
insert_license_header/insert_license.py
insert_license_header-1.3.0.dist-info/METADATA
insert_license_header-1.3.0.dist-info/WHEEL
insert_license_header-1.3.0.dist-info/entry_points.txt
insert_license_header-1.3.0.dist-info/licenses/LICENSE
insert_license_header-1.3.0.dist-info/RECORD
