Metadata-Version: 2.1
Name: insert-license-header
Version: 1.3.0
Summary: Tool to insert license headers at the beginning of text-based files.
Project-URL: repository, https://github.com/insert-license-header
Author-email: Thomas Marwitz <thomasmarwitz3@gmail.com>, Lucas Cimon <lucas.cimon@gmail.com>
License-Expression: MIT
License-File: LICENSE
Classifier: Programming Language :: Python :: 3
Classifier: Programming Language :: Python :: 3.8
Classifier: Programming Language :: Python :: 3.9
Classifier: Programming Language :: Python :: 3.10
Classifier: Programming Language :: Python :: 3.11
Requires-Python: >=3.8
Requires-Dist: rapidfuzz
